NanoparticleAtomCounter/__init__.py
NanoparticleAtomCounter/by_area.py
NanoparticleAtomCounter/by_volume.py
NanoparticleAtomCounter/count_utilities.py
NanoparticleAtomCounter/data.py
NanoparticleAtomCounter/cli/__init__.py
NanoparticleAtomCounter/cli/atom_count.py
NanoparticleAtomCounter/cli/benchmark.py
NanoparticleAtomCounter/cli/run_tests.py
benchmark/__init__.py
benchmark/atomistic_utils.py
benchmark/create_spherical_caps.py
benchmark/discrimination.py
benchmark/plot-parity.py
benchmark/test_atomcount.py
nanoparticleatomcounter-0.1.6.dist-info/licenses/LICENSE
nanoparticleatomcounter-0.1.6.dist-info/METADATA
nanoparticleatomcounter-0.1.6.dist-info/WHEEL
nanoparticleatomcounter-0.1.6.dist-info/entry_points.txt
nanoparticleatomcounter-0.1.6.dist-info/top_level.txt
nanoparticleatomcounter-0.1.6.dist-info/RECORD
