Metadata-Version: 2.4
Name: NanoparticleAtomCounter
Version: 0.1.6
Summary: Estimates atom counts in monometallic nanoparticles given radius and contact angle
Home-page: https://github.com/szilvasi-group/NanoparticleAtomCounter#readme
Author: Gbolagade Olajide, Tibor Szilvasi
Author-email: giolajide@crimson.ua.edu, tszilvasi@crimson.ua.edu
License: MIT
Project-URL: Bug Tracker, https://github.com/szilvasi-group/NanoparticleAtomCounter/issues
Project-URL: Documentation, https://github.com/szilvasi-group/NanoparticleAtomCounter#readme
Keywords: nanoparticle,tem,electron microscopy,active site,catalyst
Classifier: Development Status :: 4 - Beta
Classifier: Intended Audience :: Science/Research
Classifier: Topic :: Scientific/Engineering :: Chemistry
Classifier: License :: OSI Approved :: MIT License
Classifier: Programming Language :: Python :: 3
Classifier: Programming Language :: Python :: 3.10
Classifier: Programming Language :: Python :: 3.11
Classifier: Programming Language :: Python :: 3.12
Requires-Python: >=3.10,<3.15
License-File: LICENSE
Requires-Dist: numpy<2.3,>=1.20
Requires-Dist: pandas>=1.4
Requires-Dist: streamlit<2,>=1.4
Requires-Dist: openpyxl>=3.1
Requires-Dist: xlrd>=2.0
Provides-Extra: test
Requires-Dist: pytest<9,>=8; extra == "test"
Requires-Dist: ascii-colors; extra == "test"
Provides-Extra: benchmark
Requires-Dist: joblib<2,>=1.5; extra == "benchmark"
Requires-Dist: ase<3.27,>=3.22; extra == "benchmark"
Requires-Dist: ascii-colors; extra == "benchmark"
Requires-Dist: tqdm<5,>=4.66; extra == "benchmark"
Requires-Dist: pytest<9,>=8; extra == "benchmark"
Provides-Extra: dev
Requires-Dist: joblib<2,>=1.5; extra == "dev"
Requires-Dist: ase<3.27,>=3.22; extra == "dev"
Requires-Dist: ascii-colors; extra == "dev"
Requires-Dist: tqdm<5,>=4.66; extra == "dev"
Requires-Dist: pytest<9,>=8; extra == "dev"
Dynamic: author
Dynamic: author-email
Dynamic: classifier
Dynamic: description
Dynamic: description-content-type
Dynamic: home-page
Dynamic: keywords
Dynamic: license
Dynamic: license-file
Dynamic: project-url
Dynamic: provides-extra
Dynamic: requires-dist
Dynamic: requires-python
Dynamic: summary
